pymifare/__init__.py
pymifare/cmdactivateall.py
pymifare/cmdactivateidle.py
pymifare/cmdadvancedoutputdrive.py
pymifare/cmdauthenticate.py
pymifare/cmdchangebaudrate.py
pymifare/cmddecrementvalueblock.py
pymifare/cmdfirmware.py
pymifare/cmdgetappconfig.py
pymifare/cmdhalt.py
pymifare/cmdincrementvalueblock.py
pymifare/cmdpollbuffer.py
pymifare/cmdreadblock.py
pymifare/cmdreadi2caddress.py
pymifare/cmdreadinput.py
pymifare/cmdreadvalueblock.py
pymifare/cmdreset.py
pymifare/cmdseekfortag.py
pymifare/cmdsetantennapower.py
pymifare/cmdsetappconfig.py
pymifare/cmdseti2caddress.py
pymifare/cmdstorekey.py
pymifare/cmdwritedatablock.py
pymifare/cmdwriteoutput.py
pymifare/cmdwritesectortrailerblock.py
pymifare/cmdwritevalueblock.py
pymifare/globalvar.py
pymifare/mifare.py
pymifare/mifareasynchandler.py
pymifare/mifaredef.py
pymifare/spv1mifare_armv7.dll
pymifare/spv1mifare_armv7l.so
pymifare/spv1mifare_deb64.dll
pymifare/spv1mifare_linux_x86_64.so
pymifare/spv1mifare_ubuntu_32.dll
pymifare/spv1mifare_win.dll
pymifare/test.py
pymifare-1.0.1.dist-info/METADATA
pymifare-1.0.1.dist-info/WHEEL
pymifare-1.0.1.dist-info/entry_points.txt
pymifare-1.0.1.dist-info/top_level.txt
pymifare-1.0.1.dist-info/RECORD
