Metadata-Version: 2.1
Name: pymifare
Version: 1.0.1
Summary: pymifare python package is a part of SDK for SonMicro Mifare RFID Readers.(Mifare is a trademark of NXP). It supports all commands and handles the serial communication protocol easily. 
Home-page: http://www.sonmicro.com/
Author: SonMicro Electronics
Author-email: info@sonmicro.com
License: MIT
Requires-Dist: pyserial
Requires-Dist: pyspv1
